{
    "HUST": 20,
    "RMIT University Vietnam": 20,
    "VinUniversity": 15,
    "FPT University": 15,
    "British University Vietnam (BUV)": 15,
    "University of Greenwich Vietnam": 15,
    "University of Science and Technology of Hanoi (USTH)": 15,
    "Swinburne University of Technology (Vietnam)": 15,
    "Western Sydney University Vietnam": 15,
    "Hanoi University of Science and Technology (HUST)": 20,
    "VNU University of Engineering and Technology (VNU-UET)": 20,
    "Posts and Telecommunications Institute of Technology (PTIT)": 20,
    "Ho Chi Minh City University of Technology (HCMUT)": 20,
    "Vietnam National University, Ho Chi Minh City (VNU-HCM)": 20,
    "University of Economics and Law (UEL) - VNU-HCM": 20,
    "University of Danang - University of Science and Technology": 15,
    "University of Danang - University of Science and Technology (DUT)": 15,
    "Others": 10
  }